app/__init__.py
app/config.py
app/get_JVM.py
app/guidance.log
app/gzszf_interface_guidance.py
app/main.py
app/logger/__init__.py
app/logger/logger.py
app/models/__init__.py
app/models/model_service.py
app/models/models.py
app/resource/__init__.py
app/resource/guidance.jar
gzszf/__init__.py
gzszf/config.py
gzszf/get_JVM.py
gzszf/guidance.log
gzszf/gzszf_interface_guidance.py
gzszf/main.py
gzszf/logger/__init__.py
gzszf/logger/logger.py
gzszf/models/__init__.py
gzszf/models/model_service.py
gzszf/models/models.py
gzszf/resource/__init__.py
gzszf/resource/guidance.jar
gzszf-1.1.dist-info/METADATA
gzszf-1.1.dist-info/WHEEL
gzszf-1.1.dist-info/top_level.txt
gzszf-1.1.dist-info/RECORD
