Metadata-Version: 2.1
Name: gzszf
Version: 1.1
Summary: this is a gzszf data
Home-page: https://github.com/
Author: zhouxing
Author-email: zx@qq.com
License: MIT Licence
Platform: window10
Platform: Linux
Classifier: Programming Language :: Python :: 3.7
Classifier: License :: OSI Approved :: MIT License
Classifier: Operating System :: OS Independent
